py_rust_search.cpython-310-x86_64-linux-gnu.so
py_rust_search-0.0.1.dist-info/LICENSE
py_rust_search-0.0.1.dist-info/WHEEL
py_rust_search-0.0.1.dist-info/top_level.txt
py_rust_search-0.0.1.dist-info/RECORD
py_rust_search-0.0.1.dist-info/METADATA
