Metadata-Version: 2.1
Name: py-rust-search
Version: 0.0.1
Summary: A package for fast file searching in Python using Rust
Home-page: http://github.com/danalites/py-rust-search
Author: vrteee
Author-email: vrteee@github.com
License: GPLv3
Classifier: Development Status :: 3 - Alpha
Classifier: Programming Language :: Python :: 3
Classifier: Intended Audience :: Developers
Classifier: License :: OSI Approved :: MIT License
Classifier: Topic :: Software Development :: Libraries
Classifier: Topic :: Utilities
License-File: LICENSE
